opencefadb/__init__.py
opencefadb/_version.py
opencefadb/cli.py
opencefadb/core.py
opencefadb/db-dataset-config.jsonld
opencefadb/entities.py
opencefadb/paths.py
opencefadb/plotting.py
opencefadb/utils.py
opencefadb/_core/__init__.py
opencefadb/_core/_database_initialization.py
opencefadb/app/app.py
opencefadb/cad/__init__.py
opencefadb/cad/plotting.py
opencefadb/data/graphdb-config.ttl
opencefadb/models/__init__.py
opencefadb/models/fan_curve.py
opencefadb/models/operating_point.py
opencefadb/models/sosa.py
opencefadb/models/wikidata.py
opencefadb/postprocessing/__init__.py
opencefadb/postprocessing/dimensionless_operation_point.py
opencefadb/sparql_templates/__init__.py
opencefadb/sparql_templates/fan.py
opencefadb/sparql_templates/hdf.py
opencefadb/stores/__init__.py
opencefadb/stores/filedb/__init__.py
opencefadb/stores/filedb/database_resource.py
opencefadb/stores/filedb/hdf5filedb.py
opencefadb/stores/rdf_stores/__init__.py
opencefadb/stores/rdf_stores/graphdb/__init__.py
opencefadb/stores/rdf_stores/graphdb/administration.py
opencefadb/stores/rdf_stores/graphdb/connection.py
opencefadb/stores/rdf_stores/graphdb/query.py
opencefadb/stores/rdf_stores/graphdb/repository.py
opencefadb/stores/rdf_stores/graphdb/request_utils.py
opencefadb/stores/rdf_stores/graphdb/store.py
opencefadb/stores/rdf_stores/graphdb/url.py
opencefadb/stores/rdf_stores/rdffiledb/__init__.py
opencefadb/stores/rdf_stores/rdffiledb/rdffilestore.py
opencefadb/validation/__init__.py
opencefadb/validation/shacl/__init__.py
opencefadb/validation/shacl/templates/__init__.py
opencefadb/validation/shacl/templates/dcat.py
opencefadb/validation/shacl/templates/hdf.py
opencefadb/validation/shacl/templates/m4i.py
opencefadb/validation/shacl/templates/person.py
opencefadb/validation/shacl/templates/qudt.py
opencefadb/validation/shacl/templates/sensor.py
opencefadb/zenodo/__init__.py
opencefadb/zenodo/search.py
opencefadb-1.0.1.dist-info/licenses/LICENSE
opencefadb-1.0.1.dist-info/METADATA
opencefadb-1.0.1.dist-info/WHEEL
opencefadb-1.0.1.dist-info/entry_points.txt
opencefadb-1.0.1.dist-info/top_level.txt
opencefadb-1.0.1.dist-info/RECORD
