Metadata-Version: 2.4
Name: opencefadb
Version: 1.0.1
Summary: Python interface to the Open Centrifugal Fan Database (OpenCeFaDB).
Author-email: Matthias Probst <matthias.probst@kit.edu>
License-Expression: GPL-3.0
Project-URL: Homepage, https://github.com/matthiasprobst/openCeFaDB
Keywords: rdf,database,fan,metadata,semantic-web
Classifier: Programming Language :: Python :: 3
Classifier: Programming Language :: Python :: 3.9
Classifier: Programming Language :: Python :: 3.10
Classifier: Programming Language :: Python :: 3.11
Classifier: Programming Language :: Python :: 3.12
Classifier: Programming Language :: Python :: 3.13
Classifier: Operating System :: OS Independent
Classifier: Development Status :: 4 - Beta
Requires-Python: <3.14,>3.8
License-File: LICENSE
Requires-Dist: appdirs~=1.4.4
Requires-Dist: click~=8.1.7
Requires-Dist: rdflib~=7.1.1
Requires-Dist: requests~=2.32.4
Requires-Dist: gldb==2.1.1
Requires-Dist: ontolutils<1.0.0,>=0.27.5
Requires-Dist: h5rdmtoolbox<=3.0.0,>=2.7.2
Requires-Dist: ssnolib<=3.0.0.0,>=2.2.0.3
Requires-Dist: tqdm~=4.67.1
Requires-Dist: rdflib-endpoint[cli]
Requires-Dist: python-dotenv
Requires-Dist: pyshacl>=0.30.1
Requires-Dist: SPARQLWrapper<3.0.0,>=2.0.0
Provides-Extra: test
Requires-Dist: pytest; extra == "test"
Requires-Dist: pytest-cov; extra == "test"
Requires-Dist: toml>0.10.0; extra == "test"
Provides-Extra: complete
Requires-Dist: opencefadb[test]; extra == "complete"
Dynamic: license-file
